django_facebox-0.2.1.dist-info/DESCRIPTION.rst
django_facebox-0.2.1.dist-info/METADATA
django_facebox-0.2.1.dist-info/RECORD
django_facebox-0.2.1.dist-info/WHEEL
django_facebox-0.2.1.dist-info/metadata.json
django_facebox-0.2.1.dist-info/top_level.txt
facebox/__init__.py
facebox/models.py
facebox/static/facebox/css/facebox.css
facebox/static/facebox/img/closelabel.png
facebox/static/facebox/img/loading.gif
facebox/static/facebox/js/facebox.js
facebox/templates/facebox/base.html
facebox/templates/facebox/facebox_css.html
facebox/templates/facebox/facebox_js.html
